llm_safecall/__init__.py
llm_safecall/__main__.py
llm_safecall/budget.py
llm_safecall/cache.py
llm_safecall/cli.py
llm_safecall/env.py
llm_safecall/errors.py
llm_safecall/ids.py
llm_safecall/logger.py
llm_safecall/metrics.py
llm_safecall/moderation.py
llm_safecall/policy.py
llm_safecall/policy_yaml.py
llm_safecall/pricing.py
llm_safecall/rate_limit.py
llm_safecall/redact.py
llm_safecall/safe_call.py
llm_safecall/sanitize.py
llm_safecall/schemas.py
llm_safecall/secrets.py
llm_safecall/tools.py
llm_safecall/providers/anthropic_provider.py
llm_safecall/providers/base.py
llm_safecall/providers/mock_provider.py
llm_safecall/providers/openai_provider.py
llm_safecall-0.2.2.dist-info/licenses/LICENSE
llm_safecall-0.2.2.dist-info/METADATA
llm_safecall-0.2.2.dist-info/WHEEL
llm_safecall-0.2.2.dist-info/entry_points.txt
llm_safecall-0.2.2.dist-info/top_level.txt
llm_safecall-0.2.2.dist-info/RECORD
